{"id": "LAYOUT_VERDANTURF_TOWN", "name": "VerdanturfTown_Layout", "width": 20, "height": 20, "primary_tileset": "gTileset_General", "secondary_tileset": "gTileset_Mauville", "blockdata_filepath": "data/layouts/VerdanturfTown/map.bin", "border_filepath": "data/layouts/VerdanturfTown/border.bin", "tiles": [{"raw": 1148, "metatile_id": 124, "collision": 1, "elevation": 0, "behavior_id": 0}, {"raw": 1148, "metatile_id": 124, "collision": 1, "elevation": 0, "behavior_id": 0}, {"raw": 1149, "metatile_id": 125, "collision": 1, "elevation": 0, "behavior_id": 0}, {"raw": 1137, "metatile_id": 113, "collision": 1, "elevation": 0, "behavior_id": 12}, {"raw": 1137, "metatile_id": 113, "collision": 1, "elevation": 0, "behavior_id": 12}, {"raw": 1140, "metatile_id": 116, "collision": 1, "elevation": 0, "behavior_id": 0}, {"raw": 1193, "metatile_id": 169, "collision": 1, "elevation": 0, "behavior_id": 0}, {"raw": 1193, "metatile_id": 169, "collision": 1, "elevation": 0, "behavior_id": 0}, {"raw": 1183, "metatile_id": 159, "collision": 1, "elevation": 0, "behavior_id": 0}, {"raw": 1193, "metatile_id": 169, "collision": 1, "elevation": 0, "behavior_id": 0}, {"raw": 1148, "metatile_id": 124, "collision": 1, "elevation": 0, "behavior_id": 0}, {"raw": 1632, "metatile_id": 608, "collision": 1, "elevation": 0, "behavior_id": 0}, {"raw": 1599, "metatile_id": 575, "collision": 1, "elevation": 0, "behavior_id": 0}, {"raw": 1599, "metatile_id": 575, "collision": 1, "elevation": 0, "behavior_id": 0}, {"raw": 1598, "metatile_id": 574, "collision": 1, "elevation": 0, "behavior_id": 0}, {"raw": 1595, "metatile_id": 571, "collision": 1, "elevation": 0, "behavior_id": 0}, {"raw": 1596, "metatile_id": 572, "collision": 1, "elevation": 0, "behavior_id": 0}, {"raw": 1597, "metatile_id": 573, "collision": 1, "elevation": 0, "behavior_id": 0}, {"raw": 1605, "metatile_id": 581, "collision": 1, "elevation": 0, "behavior_id": 0}, {"raw": 1138, "metatile_id": 114, "collision": 1, "elevation": 0, "behavior_id": 0}, {"raw": 1137, "metatile_id": 113, "collision": 1, "elevation": 0, "behavior_id": 12}, {"raw": 1137, "metatile_id": 113, "collision": 1, "elevation": 0, "behavior_id": 12}, {"raw": 1137, "metatile_id": 113, "collision": 1, "elevation": 0, "behavior_id": 12}, {"raw": 1137, "metatile_id": 113, "collision": 1, "elevation": 0, "behavior_id": 12}, {"raw": 1137, "metatile_id": 113, "collision": 1, "elevation": 0, "behavior_id": 12}, {"raw": 1141, "metatile_id": 117, "collision": 1, "elevation": 0, "behavior_id": 0}, {"raw": 1140, "metatile_id": 116, "collision": 1, "elevation": 0, "behavior_id": 0}, {"raw": 1169, "metatile_id": 145, "collision": 1, "elevation": 0, "behavior_id": 0}, {"raw": 167, "metatile_id": 167, "collision": 0, "elevation": 0, "behavior_id": 96}, {"raw": 1169, "metatile_id": 145, "collision": 1, "elevation": 0, "behavior_id": 0}, {"raw": 1169, "metatile_id": 145, "collision": 1, "elevation": 0, "behavior_id": 0}, {"raw": 1072, "metatile_id": 48, "collision": 1, "elevation": 0, "behavior_id": 0}, {"raw": 1073, "metatile_id": 49, "collision": 1, "elevation": 0, "behavior_id": 0}, {"raw": 1074, "metatile_id": 50, "collision": 1, "elevation": 0, "behavior_id": 0}, {"raw": 1075, "metatile_id": 51, "collision": 1, "elevation": 0, "behavior_id": 0}, {"raw": 1104, "metatile_id": 80, "collision": 1, "elevation": 0, "behavior_id": 0}, {"raw": 1105, "metatile_id": 81, "collision": 1, "elevation": 0, "behavior_id": 0}, {"raw": 1106, "metatile_id": 82, "collision": 1, "elevation": 0, "behavior_id": 0}, {"raw": 1107, "metatile_id": 83, "collision": 1, "elevation": 0, "behavior_id": 0}, {"raw": 1146, "metatile_id": 122, "collision": 1, "elevation": 0, "behavior_id": 0}, {"raw": 1148, "metatile_id": 124, "collision": 1, "elevation": 0, "behavior_id": 0}, {"raw": 1148, "metatile_id": 124, "collision": 1, "elevation": 0, "behavior_id": 0}, {"raw": 1148, "metatile_id": 124, "collision": 1, "elevation": 0, "behavior_id": 0}, {"raw": 1148, "metatile_id": 124, "collision": 1, "elevation": 0, "behavior_id": 0}, {"raw": 1148, "metatile_id": 124, "collision": 1, "elevation": 0, "behavior_id": 0}, {"raw": 1149, "metatile_id": 125, "collision": 1, "elevation": 0, "behavior_id": 0}, {"raw": 1138, "metatile_id": 114, "collision": 1, "elevation": 0, "behavior_id": 0}, {"raw": 12804, "metatile_id": 516, "collision": 0, "elevation": 3, "behavior_id": 7}, {"raw": 12804, "metatile_id": 516, "collision": 0, "elevation": 3, "behavior_id": 7}, {"raw": 12804, "metatile_id": 516, "collision": 0, "elevation": 3, "behavior_id": 7}, {"raw": 14256, "metatile_id": 944, "collision": 1, "elevation": 3, "behavior_id": 0}, {"raw": 1080, "metatile_id": 56, "collision": 1, "elevation": 0, "behavior_id": 0}, {"raw": 1081, "metatile_id": 57, "collision": 1, "elevation": 0, "behavior_id": 0}, {"raw": 1082, "metatile_id": 58, "collision": 1, "elevation": 0, "behavior_id": 0}, {"raw": 1083, "metatile_id": 59, "collision": 1, "elevation": 0, "behavior_id": 0}, {"raw": 1112, "metatile_id": 88, "collision": 1, "elevation": 0, "behavior_id": 0}, {"raw": 1113, "metatile_id": 89, "collision": 1, "elevation": 0, "behavior_id": 0}, {"raw": 1114, "metatile_id": 90, "collision": 1, "elevation": 0, "behavior_id": 0}, {"raw": 1115, "metatile_id": 91, "collision": 1, "elevation": 0, "behavior_id": 0}, {"raw": 12993, "metatile_id": 705, "collision": 0, "elevation": 3, "behavior_id": 0}, {"raw": 1230, "metatile_id": 206, "collision": 1, "elevation": 0, "behavior_id": 0}, {"raw": 1970, "metatile_id": 946, "collision": 1, "elevation": 0, "behavior_id": 0}, {"raw": 1971, "metatile_id": 947, "collision": 1, "elevation": 0, "behavior_id": 0}, {"raw": 1972, "metatile_id": 948, "collision": 1, "elevation": 0, "behavior_id": 0}, {"raw": 1973, "metatile_id": 949, "collision": 1, "elevation": 0, "behavior_id": 0}, {"raw": 1974, "metatile_id": 950, "collision": 1, "elevation": 0, "behavior_id": 0}, {"raw": 1581, "metatile_id": 557, "collision": 1, "elevation": 0, "behavior_id": 0}, {"raw": 1027, "metatile_id": 3, "collision": 1, "elevation": 0, "behavior_id": 0}, {"raw": 12804, "metatile_id": 516, "collision": 0, "elevation": 3, "behavior_id": 7}, {"raw": 12804, "metatile_id": 516, "collision": 0, "elevation": 3, "behavior_id": 7}, {"raw": 14158, "metatile_id": 846, "collision": 1, "elevation": 3, "behavior_id": 7}, {"raw": 1120, "metatile_id": 96, "collision": 1, "elevation": 0, "behavior_id": 0}, {"raw": 1089, "metatile_id": 65, "collision": 1, "elevation": 0, "behavior_id": 105}, {"raw": 1090, "metatile_id": 66, "collision": 1, "elevation": 0, "behavior_id": 0}, {"raw": 1091, "metatile_id": 67, "collision": 1, "elevation": 0, "behavior_id": 0}, {"raw": 1120, "metatile_id": 96, "collision": 1, "elevation": 0, "behavior_id": 0}, {"raw": 1121, "metatile_id": 97, "collision": 1, "elevation": 0, "behavior_id": 105}, {"raw": 1122, "metatile_id": 98, "collision": 1, "elevation": 0, "behavior_id": 0}, {"raw": 1123, "metatile_id": 99, "collision": 1, "elevation": 0, "behavior_id": 0}, {"raw": 1223, "metatile_id": 199, "collision": 1, "elevation": 0, "behavior_id": 0}, {"raw": 1223, "metatile_id": 199, "collision": 1, "elevation": 0, "behavior_id": 0}, {"raw": 1978, "metatile_id": 954, "collision": 1, "elevation": 0, "behavior_id": 0}, {"raw": 1979, "metatile_id": 955, "collision": 1, "elevation": 0, "behavior_id": 0}, {"raw": 1980, "metatile_id": 956, "collision": 1, "elevation": 0, "behavior_id": 0}, {"raw": 1981, "metatile_id": 957, "collision": 1, "elevation": 0, "behavior_id": 0}, {"raw": 1982, "metatile_id": 958, "collision": 1, "elevation": 0, "behavior_id": 0}, {"raw": 12804, "metatile_id": 516, "collision": 0, "elevation": 3, "behavior_id": 7}, {"raw": 12804, "metatile_id": 516, "collision": 0, "elevation": 3, "behavior_id": 7}, {"raw": 12804, "metatile_id": 516, "collision": 0, "elevation": 3, "behavior_id": 7}, {"raw": 12804, "metatile_id": 516, "collision": 0, "elevation": 3, "behavior_id": 7}, {"raw": 14115, "metatile_id": 803, "collision": 1, "elevation": 3, "behavior_id": 0}, {"raw": 12804, "metatile_id": 516, "collision": 0, "elevation": 3, "behavior_id": 7}, {"raw": 12289, "metatile_id": 1, "collision": 0, "elevation": 3, "behavior_id": 0}, {"raw": 12289, "metatile_id": 1, "collision": 0, "elevation": 3, "behavior_id": 0}, {"raw": 12805, "metatile_id": 517, "collision": 0, "elevation": 3, "behavior_id": 7}, {"raw": 12804, "metatile_id": 516, "collision": 0, "elevation": 3, "behavior_id": 7}, {"raw": 12289, "metatile_id": 1, "collision": 0, "elevation": 3, "behavior_id": 0}, {"raw": 12289, "metatile_id": 1, "collision": 0, "elevation": 3, "behavior_id": 0}, {"raw": 12804, "metatile_id": 516, "collision": 0, "elevation": 3, "behavior_id": 7}, {"raw": 1737, "metatile_id": 713, "collision": 1, "elevation": 0, "behavior_id": 0}, {"raw": 1223, "metatile_id": 199, "collision": 1, "elevation": 0, "behavior_id": 0}, {"raw": 1986, "metatile_id": 962, "collision": 1, "elevation": 0, "behavior_id": 0}, {"raw": 1987, "metatile_id": 963, "collision": 1, "elevation": 0, "behavior_id": 0}, {"raw": 1988, "metatile_id": 964, "collision": 1, "elevation": 0, "behavior_id": 0}, {"raw": 1989, "metatile_id": 965, "collision": 1, "elevation": 0, "behavior_id": 0}, {"raw": 1990, "metatile_id": 966, "collision": 1, "elevation": 0, "behavior_id": 0}, {"raw": 12804, "metatile_id": 516, "collision": 0, "elevation": 3, "behavior_id": 7}, {"raw": 12804, "metatile_id": 516, "collision": 0, "elevation": 3, "behavior_id": 7}, {"raw": 12804, "metatile_id": 516, "collision": 0, "elevation": 3, "behavior_id": 7}, {"raw": 12804, "metatile_id": 516, "collision": 0, "elevation": 3, "behavior_id": 7}, {"raw": 12804, "metatile_id": 516, "collision": 0, "elevation": 3, "behavior_id": 7}, {"raw": 12804, "metatile_id": 516, "collision": 0, "elevation": 3, "behavior_id": 7}, {"raw": 12289, "metatile_id": 1, "collision": 0, "elevation": 3, "behavior_id": 0}, {"raw": 12289, "metatile_id": 1, "collision": 0, "elevation": 3, "behavior_id": 0}, {"raw": 12804, "metatile_id": 516, "collision": 0, "elevation": 3, "behavior_id": 7}, {"raw": 12804, "metatile_id": 516, "collision": 0, "elevation": 3, "behavior_id": 7}, {"raw": 12289, "metatile_id": 1, "collision": 0, "elevation": 3, "behavior_id": 0}, {"raw": 12289, "metatile_id": 1, "collision": 0, "elevation": 3, "behavior_id": 0}, {"raw": 12804, "metatile_id": 516, "collision": 0, "elevation": 3, "behavior_id": 7}, {"raw": 12804, "metatile_id": 516, "collision": 0, "elevation": 3, "behavior_id": 7}, {"raw": 1223, "metatile_id": 199, "collision": 1, "elevation": 0, "behavior_id": 0}, {"raw": 1994, "metatile_id": 970, "collision": 1, "elevation": 0, "behavior_id": 0}, {"raw": 1995, "metatile_id": 971, "collision": 1, "elevation": 0, "behavior_id": 0}, {"raw": 1996, "metatile_id": 972, "collision": 1, "elevation": 0, "behavior_id": 105}, {"raw": 1997, "metatile_id": 973, "collision": 1, "elevation": 0, "behavior_id": 0}, {"raw": 1998, "metatile_id": 974, "collision": 1, "elevation": 0, "behavior_id": 0}, {"raw": 12804, "metatile_id": 516, "collision": 0, "elevation": 3, "behavior_id": 7}, {"raw": 12817, "metatile_id": 529, "collision": 0, "elevation": 3, "behavior_id": 0}, {"raw": 12804, "metatile_id": 516, "collision": 0, "elevation": 3, "behavior_id": 7}, {"raw": 12804, "metatile_id": 516, "collision": 0, "elevation": 3, "behavior_id": 7}, {"raw": 12804, "metatile_id": 516, "collision": 0, "elevation": 3, "behavior_id": 7}, {"raw": 12804, "metatile_id": 516, "collision": 0, "elevation": 3, "behavior_id": 7}, {"raw": 12289, "metatile_id": 1, "collision": 0, "elevation": 3, "behavior_id": 0}, {"raw": 12289, "metatile_id": 1, "collision": 0, "elevation": 3, "behavior_id": 0}, {"raw": 1027, "metatile_id": 3, "collision": 1, "elevation": 0, "behavior_id": 0}, {"raw": 12804, "metatile_id": 516, "collision": 0, "elevation": 3, "behavior_id": 7}, {"raw": 12289, "metatile_id": 1, "collision": 0, "elevation": 3, "behavior_id": 0}, {"raw": 12289, "metatile_id": 1, "collision": 0, "elevation": 3, "behavior_id": 0}, {"raw": 12804, "metatile_id": 516, "collision": 0, "elevation": 3, "behavior_id": 7}, {"raw": 12804, "metatile_id": 516, "collision": 0, "elevation": 3, "behavior_id": 7}, {"raw": 1223, "metatile_id": 199, "collision": 1, "elevation": 0, "behavior_id": 0}, {"raw": 2002, "metatile_id": 978, "collision": 1, "elevation": 0, "behavior_id": 0}, {"raw": 2003, "metatile_id": 979, "collision": 1, "elevation": 0, "behavior_id": 0}, {"raw": 2004, "metatile_id": 980, "collision": 1, "elevation": 0, "behavior_id": 105}, {"raw": 2005, "metatile_id": 981, "collision": 1, "elevation": 0, "behavior_id": 0}, {"raw": 2006, "metatile_id": 982, "collision": 1, "elevation": 0, "behavior_id": 0}, {"raw": 12289, "metatile_id": 1, "collision": 0, "elevation": 3, "behavior_id": 0}, {"raw": 12804, "metatile_id": 516, "collision": 0, "elevation": 3, "behavior_id": 7}, {"raw": 12804, "metatile_id": 516, "collision": 0, "elevation": 3, "behavior_id": 7}, {"raw": 12804, "metatile_id": 516, "collision": 0, "elevation": 3, "behavior_id": 7}, {"raw": 12804, "metatile_id": 516, "collision": 0, "elevation": 3, "behavior_id": 7}, {"raw": 12289, "metatile_id": 1, "collision": 0, "elevation": 3, "behavior_id": 0}, {"raw": 12289, "metatile_id": 1, "collision": 0, "elevation": 3, "behavior_id": 0}, {"raw": 12289, "metatile_id": 1, "collision": 0, "elevation": 3, "behavior_id": 0}, {"raw": 12289, "metatile_id": 1, "collision": 0, "elevation": 3, "behavior_id": 0}, {"raw": 12289, "metatile_id": 1, "collision": 0, "elevation": 3, "behavior_id": 0}, {"raw": 12289, "metatile_id": 1, "collision": 0, "elevation": 3, "behavior_id": 0}, {"raw": 12289, "metatile_id": 1, "collision": 0, "elevation": 3, "behavior_id": 0}, {"raw": 12804, "metatile_id": 516, "collision": 0, "elevation": 3, "behavior_id": 7}, {"raw": 12804, "metatile_id": 516, "collision": 0, "elevation": 3, "behavior_id": 7}, {"raw": 1737, "metatile_id": 713, "collision": 1, "elevation": 0, "behavior_id": 0}, {"raw": 1027, "metatile_id": 3, "collision": 1, "elevation": 0, "behavior_id": 0}, {"raw": 12804, "metatile_id": 516, "collision": 0, "elevation": 3, "behavior_id": 7}, {"raw": 12289, "metatile_id": 1, "collision": 0, "elevation": 3, "behavior_id": 0}, {"raw": 12289, "metatile_id": 1, "collision": 0, "elevation": 3, "behavior_id": 0}, {"raw": 12289, "metatile_id": 1, "collision": 0, "elevation": 3, "behavior_id": 0}, {"raw": 12289, "metatile_id": 1, "collision": 0, "elevation": 3, "behavior_id": 0}, {"raw": 12289, "metatile_id": 1, "collision": 0, "elevation": 3, "behavior_id": 0}, {"raw": 12289, "metatile_id": 1, "collision": 0, "elevation": 3, "behavior_id": 0}, {"raw": 12289, "metatile_id": 1, "collision": 0, "elevation": 3, "behavior_id": 0}, {"raw": 12289, "metatile_id": 1, "collision": 0, "elevation": 3, "behavior_id": 0}, {"raw": 12289, "metatile_id": 1, "collision": 0, "elevation": 3, "behavior_id": 0}, {"raw": 12289, "metatile_id": 1, "collision": 0, "elevation": 3, "behavior_id": 0}, {"raw": 12289, "metatile_id": 1, "collision": 0, "elevation": 3, "behavior_id": 0}, {"raw": 12289, "metatile_id": 1, "collision": 0, "elevation": 3, "behavior_id": 0}, {"raw": 12289, "metatile_id": 1, "collision": 0, "elevation": 3, "behavior_id": 0}, {"raw": 12289, "metatile_id": 1, "collision": 0, "elevation": 3, "behavior_id": 0}, {"raw": 12805, "metatile_id": 517, "collision": 0, "elevation": 3, "behavior_id": 7}, {"raw": 12804, "metatile_id": 516, "collision": 0, "elevation": 3, "behavior_id": 7}, {"raw": 12804, "metatile_id": 516, "collision": 0, "elevation": 3, "behavior_id": 7}, {"raw": 12804, "metatile_id": 516, "collision": 0, "elevation": 3, "behavior_id": 7}, {"raw": 12804, "metatile_id": 516, "collision": 0, "elevation": 3, "behavior_id": 7}, {"raw": 12804, "metatile_id": 516, "collision": 0, "elevation": 3, "behavior_id": 7}, {"raw": 12804, "metatile_id": 516, "collision": 0, "elevation": 3, "behavior_id": 7}, {"raw": 12289, "metatile_id": 1, "collision": 0, "elevation": 3, "behavior_id": 0}, {"raw": 12289, "metatile_id": 1, "collision": 0, "elevation": 3, "behavior_id": 0}, {"raw": 12289, "metatile_id": 1, "collision": 0, "elevation": 3, "behavior_id": 0}, {"raw": 12289, "metatile_id": 1, "collision": 0, "elevation": 3, "behavior_id": 0}, {"raw": 12289, "metatile_id": 1, "collision": 0, "elevation": 3, "behavior_id": 0}, {"raw": 12289, "metatile_id": 1, "collision": 0, "elevation": 3, "behavior_id": 0}, {"raw": 12289, "metatile_id": 1, "collision": 0, "elevation": 3, "behavior_id": 0}, {"raw": 12289, "metatile_id": 1, "collision": 0, "elevation": 3, "behavior_id": 0}, {"raw": 12289, "metatile_id": 1, "collision": 0, "elevation": 3, "behavior_id": 0}, {"raw": 12289, "metatile_id": 1, "collision": 0, "elevation": 3, "behavior_id": 0}, {"raw": 12289, "metatile_id": 1, "collision": 0, "elevation": 3, "behavior_id": 0}, {"raw": 12289, "metatile_id": 1, "collision": 0, "elevation": 3, "behavior_id": 0}, {"raw": 12804, "metatile_id": 516, "collision": 0, "elevation": 3, "behavior_id": 7}, {"raw": 12805, "metatile_id": 517, "collision": 0, "elevation": 3, "behavior_id": 7}, {"raw": 12804, "metatile_id": 516, "collision": 0, "elevation": 3, "behavior_id": 7}, {"raw": 12804, "metatile_id": 516, "collision": 0, "elevation": 3, "behavior_id": 7}, {"raw": 12820, "metatile_id": 532, "collision": 0, "elevation": 3, "behavior_id": 0}, {"raw": 12804, "metatile_id": 516, "collision": 0, "elevation": 3, "behavior_id": 7}, {"raw": 12804, "metatile_id": 516, "collision": 0, "elevation": 3, "behavior_id": 7}, {"raw": 12804, "metatile_id": 516, "collision": 0, "elevation": 3, "behavior_id": 7}, {"raw": 12805, "metatile_id": 517, "collision": 0, "elevation": 3, "behavior_id": 7}, {"raw": 12804, "metatile_id": 516, "collision": 0, "elevation": 3, "behavior_id": 7}, {"raw": 12805, "metatile_id": 517, "collision": 0, "elevation": 3, "behavior_id": 7}, {"raw": 12804, "metatile_id": 516, "collision": 0, "elevation": 3, "behavior_id": 7}, {"raw": 12804, "metatile_id": 516, "collision": 0, "elevation": 3, "behavior_id": 7}, {"raw": 12804, "metatile_id": 516, "collision": 0, "elevation": 3, "behavior_id": 7}, {"raw": 12817, "metatile_id": 529, "collision": 0, "elevation": 3, "behavior_id": 0}, {"raw": 12804, "metatile_id": 516, "collision": 0, "elevation": 3, "behavior_id": 7}, {"raw": 12804, "metatile_id": 516, "collision": 0, "elevation": 3, "behavior_id": 7}, {"raw": 12289, "metatile_id": 1, "collision": 0, "elevation": 3, "behavior_id": 0}, {"raw": 12289, "metatile_id": 1, "collision": 0, "elevation": 3, "behavior_id": 0}, {"raw": 12804, "metatile_id": 516, "collision": 0, "elevation": 3, "behavior_id": 7}, {"raw": 12804, "metatile_id": 516, "collision": 0, "elevation": 3, "behavior_id": 7}, {"raw": 12804, "metatile_id": 516, "collision": 0, "elevation": 3, "behavior_id": 7}, {"raw": 12804, "metatile_id": 516, "collision": 0, "elevation": 3, "behavior_id": 7}, {"raw": 12804, "metatile_id": 516, "collision": 0, "elevation": 3, "behavior_id": 7}, {"raw": 13192, "metatile_id": 904, "collision": 0, "elevation": 3, "behavior_id": 0}, {"raw": 13193, "metatile_id": 905, "collision": 0, "elevation": 3, "behavior_id": 0}, {"raw": 13193, "metatile_id": 905, "collision": 0, "elevation": 3, "behavior_id": 0}, {"raw": 13194, "metatile_id": 906, "collision": 0, "elevation": 3, "behavior_id": 0}, {"raw": 12805, "metatile_id": 517, "collision": 0, "elevation": 3, "behavior_id": 7}, {"raw": 12804, "metatile_id": 516, "collision": 0, "elevation": 3, "behavior_id": 7}, {"raw": 12805, "metatile_id": 517, "collision": 0, "elevation": 3, "behavior_id": 7}, {"raw": 12804, "metatile_id": 516, "collision": 0, "elevation": 3, "behavior_id": 7}, {"raw": 13192, "metatile_id": 904, "collision": 0, "elevation": 3, "behavior_id": 0}, {"raw": 13193, "metatile_id": 905, "collision": 0, "elevation": 3, "behavior_id": 0}, {"raw": 13193, "metatile_id": 905, "collision": 0, "elevation": 3, "behavior_id": 0}, {"raw": 13193, "metatile_id": 905, "collision": 0, "elevation": 3, "behavior_id": 0}, {"raw": 13194, "metatile_id": 906, "collision": 0, "elevation": 3, "behavior_id": 0}, {"raw": 12289, "metatile_id": 1, "collision": 0, "elevation": 3, "behavior_id": 0}, {"raw": 12289, "metatile_id": 1, "collision": 0, "elevation": 3, "behavior_id": 0}, {"raw": 12805, "metatile_id": 517, "collision": 0, "elevation": 3, "behavior_id": 7}, {"raw": 12804, "metatile_id": 516, "collision": 0, "elevation": 3, "behavior_id": 7}, {"raw": 12804, "metatile_id": 516, "collision": 0, "elevation": 3, "behavior_id": 7}, {"raw": 12804, "metatile_id": 516, "collision": 0, "elevation": 3, "behavior_id": 7}, {"raw": 12805, "metatile_id": 517, "collision": 0, "elevation": 3, "behavior_id": 7}, {"raw": 1936, "metatile_id": 912, "collision": 1, "elevation": 0, "behavior_id": 0}, {"raw": 1937, "metatile_id": 913, "collision": 1, "elevation": 0, "behavior_id": 0}, {"raw": 1937, "metatile_id": 913, "collision": 1, "elevation": 0, "behavior_id": 0}, {"raw": 1938, "metatile_id": 914, "collision": 1, "elevation": 0, "behavior_id": 0}, {"raw": 1869, "metatile_id": 845, "collision": 1, "elevation": 0, "behavior_id": 7}, {"raw": 1869, "metatile_id": 845, "collision": 1, "elevation": 0, "behavior_id": 7}, {"raw": 1869, "metatile_id": 845, "collision": 1, "elevation": 0, "behavior_id": 7}, {"raw": 1869, "metatile_id": 845, "collision": 1, "elevation": 0, "behavior_id": 7}, {"raw": 1936, "metatile_id": 912, "collision": 1, "elevation": 0, "behavior_id": 0}, {"raw": 1937, "metatile_id": 913, "collision": 1, "elevation": 0, "behavior_id": 0}, {"raw": 1937, "metatile_id": 913, "collision": 1, "elevation": 0, "behavior_id": 0}, {"raw": 1937, "metatile_id": 913, "collision": 1, "elevation": 0, "behavior_id": 0}, {"raw": 1938, "metatile_id": 914, "collision": 1, "elevation": 0, "behavior_id": 0}, {"raw": 12289, "metatile_id": 1, "collision": 0, "elevation": 3, "behavior_id": 0}, {"raw": 12289, "metatile_id": 1, "collision": 0, "elevation": 3, "behavior_id": 0}, {"raw": 12805, "metatile_id": 517, "collision": 0, "elevation": 3, "behavior_id": 7}, {"raw": 13192, "metatile_id": 904, "collision": 0, "elevation": 3, "behavior_id": 0}, {"raw": 13193, "metatile_id": 905, "collision": 0, "elevation": 3, "behavior_id": 0}, {"raw": 13193, "metatile_id": 905, "collision": 0, "elevation": 3, "behavior_id": 0}, {"raw": 13194, "metatile_id": 906, "collision": 0, "elevation": 3, "behavior_id": 0}, {"raw": 1944, "metatile_id": 920, "collision": 1, "elevation": 0, "behavior_id": 0}, {"raw": 1945, "metatile_id": 921, "collision": 1, "elevation": 0, "behavior_id": 0}, {"raw": 1931, "metatile_id": 907, "collision": 1, "elevation": 0, "behavior_id": 0}, {"raw": 1932, "metatile_id": 908, "collision": 1, "elevation": 0, "behavior_id": 0}, {"raw": 12820, "metatile_id": 532, "collision": 0, "elevation": 3, "behavior_id": 0}, {"raw": 12804, "metatile_id": 516, "collision": 0, "elevation": 3, "behavior_id": 7}, {"raw": 12819, "metatile_id": 531, "collision": 0, "elevation": 3, "behavior_id": 0}, {"raw": 12818, "metatile_id": 530, "collision": 0, "elevation": 3, "behavior_id": 0}, {"raw": 1944, "metatile_id": 920, "collision": 1, "elevation": 0, "behavior_id": 0}, {"raw": 1931, "metatile_id": 907, "collision": 1, "elevation": 0, "behavior_id": 0}, {"raw": 1945, "metatile_id": 921, "collision": 1, "elevation": 0, "behavior_id": 0}, {"raw": 1931, "metatile_id": 907, "collision": 1, "elevation": 0, "behavior_id": 0}, {"raw": 1932, "metatile_id": 908, "collision": 1, "elevation": 0, "behavior_id": 0}, {"raw": 12289, "metatile_id": 1, "collision": 0, "elevation": 3, "behavior_id": 0}, {"raw": 12289, "metatile_id": 1, "collision": 0, "elevation": 3, "behavior_id": 0}, {"raw": 12805, "metatile_id": 517, "collision": 0, "elevation": 3, "behavior_id": 7}, {"raw": 1936, "metatile_id": 912, "collision": 1, "elevation": 0, "behavior_id": 0}, {"raw": 1937, "metatile_id": 913, "collision": 1, "elevation": 0, "behavior_id": 0}, {"raw": 1937, "metatile_id": 913, "collision": 1, "elevation": 0, "behavior_id": 0}, {"raw": 1938, "metatile_id": 914, "collision": 1, "elevation": 0, "behavior_id": 0}, {"raw": 1952, "metatile_id": 928, "collision": 1, "elevation": 0, "behavior_id": 0}, {"raw": 1953, "metatile_id": 929, "collision": 1, "elevation": 0, "behavior_id": 105}, {"raw": 1939, "metatile_id": 915, "collision": 1, "elevation": 0, "behavior_id": 0}, {"raw": 1940, "metatile_id": 916, "collision": 1, "elevation": 0, "behavior_id": 0}, {"raw": 12804, "metatile_id": 516, "collision": 0, "elevation": 3, "behavior_id": 7}, {"raw": 12821, "metatile_id": 533, "collision": 0, "elevation": 3, "behavior_id": 0}, {"raw": 12820, "metatile_id": 532, "collision": 0, "elevation": 3, "behavior_id": 0}, {"raw": 1027, "metatile_id": 3, "collision": 1, "elevation": 0, "behavior_id": 0}, {"raw": 1952, "metatile_id": 928, "collision": 1, "elevation": 0, "behavior_id": 0}, {"raw": 1939, "metatile_id": 915, "collision": 1, "elevation": 0, "behavior_id": 0}, {"raw": 1953, "metatile_id": 929, "collision": 1, "elevation": 0, "behavior_id": 105}, {"raw": 1939, "metatile_id": 915, "collision": 1, "elevation": 0, "behavior_id": 0}, {"raw": 1940, "metatile_id": 916, "collision": 1, "elevation": 0, "behavior_id": 0}, {"raw": 12289, "metatile_id": 1, "collision": 0, "elevation": 3, "behavior_id": 0}, {"raw": 12289, "metatile_id": 1, "collision": 0, "elevation": 3, "behavior_id": 0}, {"raw": 12805, "metatile_id": 517, "collision": 0, "elevation": 3, "behavior_id": 7}, {"raw": 1944, "metatile_id": 920, "collision": 1, "elevation": 0, "behavior_id": 0}, {"raw": 1945, "metatile_id": 921, "collision": 1, "elevation": 0, "behavior_id": 0}, {"raw": 1931, "metatile_id": 907, "collision": 1, "elevation": 0, "behavior_id": 0}, {"raw": 1932, "metatile_id": 908, "collision": 1, "elevation": 0, "behavior_id": 0}, {"raw": 1716, "metatile_id": 692, "collision": 1, "elevation": 0, "behavior_id": 0}, {"raw": 12805, "metatile_id": 517, "collision": 0, "elevation": 3, "behavior_id": 7}, {"raw": 12804, "metatile_id": 516, "collision": 0, "elevation": 3, "behavior_id": 7}, {"raw": 12804, "metatile_id": 516, "collision": 0, "elevation": 3, "behavior_id": 7}, {"raw": 12805, "metatile_id": 517, "collision": 0, "elevation": 3, "behavior_id": 7}, {"raw": 12805, "metatile_id": 517, "collision": 0, "elevation": 3, "behavior_id": 7}, {"raw": 12804, "metatile_id": 516, "collision": 0, "elevation": 3, "behavior_id": 7}, {"raw": 12805, "metatile_id": 517, "collision": 0, "elevation": 3, "behavior_id": 7}, {"raw": 12805, "metatile_id": 517, "collision": 0, "elevation": 3, "behavior_id": 7}, {"raw": 12804, "metatile_id": 516, "collision": 0, "elevation": 3, "behavior_id": 7}, {"raw": 12289, "metatile_id": 1, "collision": 0, "elevation": 3, "behavior_id": 0}, {"raw": 12289, "metatile_id": 1, "collision": 0, "elevation": 3, "behavior_id": 0}, {"raw": 12289, "metatile_id": 1, "collision": 0, "elevation": 3, "behavior_id": 0}, {"raw": 12289, "metatile_id": 1, "collision": 0, "elevation": 3, "behavior_id": 0}, {"raw": 12804, "metatile_id": 516, "collision": 0, "elevation": 3, "behavior_id": 7}, {"raw": 12804, "metatile_id": 516, "collision": 0, "elevation": 3, "behavior_id": 7}, {"raw": 1952, "metatile_id": 928, "collision": 1, "elevation": 0, "behavior_id": 0}, {"raw": 1953, "metatile_id": 929, "collision": 1, "elevation": 0, "behavior_id": 105}, {"raw": 1939, "metatile_id": 915, "collision": 1, "elevation": 0, "behavior_id": 0}, {"raw": 1940, "metatile_id": 916, "collision": 1, "elevation": 0, "behavior_id": 0}, {"raw": 1724, "metatile_id": 700, "collision": 1, "elevation": 0, "behavior_id": 0}, {"raw": 12804, "metatile_id": 516, "collision": 0, "elevation": 3, "behavior_id": 7}, {"raw": 12805, "metatile_id": 517, "collision": 0, "elevation": 3, "behavior_id": 7}, {"raw": 12805, "metatile_id": 517, "collision": 0, "elevation": 3, "behavior_id": 7}, {"raw": 12804, "metatile_id": 516, "collision": 0, "elevation": 3, "behavior_id": 7}, {"raw": 12804, "metatile_id": 516, "collision": 0, "elevation": 3, "behavior_id": 7}, {"raw": 12804, "metatile_id": 516, "collision": 0, "elevation": 3, "behavior_id": 7}, {"raw": 12805, "metatile_id": 517, "collision": 0, "elevation": 3, "behavior_id": 7}, {"raw": 12804, "metatile_id": 516, "collision": 0, "elevation": 3, "behavior_id": 7}, {"raw": 12804, "metatile_id": 516, "collision": 0, "elevation": 3, "behavior_id": 7}, {"raw": 12804, "metatile_id": 516, "collision": 0, "elevation": 3, "behavior_id": 7}, {"raw": 12805, "metatile_id": 517, "collision": 0, "elevation": 3, "behavior_id": 7}, {"raw": 12804, "metatile_id": 516, "collision": 0, "elevation": 3, "behavior_id": 7}, {"raw": 12805, "metatile_id": 517, "collision": 0, "elevation": 3, "behavior_id": 7}, {"raw": 12804, "metatile_id": 516, "collision": 0, "elevation": 3, "behavior_id": 7}, {"raw": 12805, "metatile_id": 517, "collision": 0, "elevation": 3, "behavior_id": 7}, {"raw": 12804, "metatile_id": 516, "collision": 0, "elevation": 3, "behavior_id": 7}, {"raw": 12804, "metatile_id": 516, "collision": 0, "elevation": 3, "behavior_id": 7}, {"raw": 12804, "metatile_id": 516, "collision": 0, "elevation": 3, "behavior_id": 7}, {"raw": 12804, "metatile_id": 516, "collision": 0, "elevation": 3, "behavior_id": 7}, {"raw": 12993, "metatile_id": 705, "collision": 0, "elevation": 3, "behavior_id": 0}, {"raw": 12822, "metatile_id": 534, "collision": 0, "elevation": 3, "behavior_id": 0}, {"raw": 12804, "metatile_id": 516, "collision": 0, "elevation": 3, "behavior_id": 7}, {"raw": 12805, "metatile_id": 517, "collision": 0, "elevation": 3, "behavior_id": 7}, {"raw": 12804, "metatile_id": 516, "collision": 0, "elevation": 3, "behavior_id": 7}, {"raw": 12804, "metatile_id": 516, "collision": 0, "elevation": 3, "behavior_id": 7}, {"raw": 12821, "metatile_id": 533, "collision": 0, "elevation": 3, "behavior_id": 0}, {"raw": 12993, "metatile_id": 705, "collision": 0, "elevation": 3, "behavior_id": 0}, {"raw": 12993, "metatile_id": 705, "collision": 0, "elevation": 3, "behavior_id": 0}, {"raw": 12993, "metatile_id": 705, "collision": 0, "elevation": 3, "behavior_id": 0}, {"raw": 12993, "metatile_id": 705, "collision": 0, "elevation": 3, "behavior_id": 0}, {"raw": 12804, "metatile_id": 516, "collision": 0, "elevation": 3, "behavior_id": 7}, {"raw": 12820, "metatile_id": 532, "collision": 0, "elevation": 3, "behavior_id": 0}, {"raw": 12805, "metatile_id": 517, "collision": 0, "elevation": 3, "behavior_id": 7}, {"raw": 12805, "metatile_id": 517, "collision": 0, "elevation": 3, "behavior_id": 7}, {"raw": 12804, "metatile_id": 516, "collision": 0, "elevation": 3, "behavior_id": 7}, {"raw": 12804, "metatile_id": 516, "collision": 0, "elevation": 3, "behavior_id": 7}, {"raw": 12804, "metatile_id": 516, "collision": 0, "elevation": 3, "behavior_id": 7}, {"raw": 12804, "metatile_id": 516, "collision": 0, "elevation": 3, "behavior_id": 7}, {"raw": 12993, "metatile_id": 705, "collision": 0, "elevation": 3, "behavior_id": 0}, {"raw": 1223, "metatile_id": 199, "collision": 1, "elevation": 0, "behavior_id": 0}, {"raw": 12993, "metatile_id": 705, "collision": 0, "elevation": 3, "behavior_id": 0}, {"raw": 12993, "metatile_id": 705, "collision": 0, "elevation": 3, "behavior_id": 0}, {"raw": 12822, "metatile_id": 534, "collision": 0, "elevation": 3, "behavior_id": 0}, {"raw": 12804, "metatile_id": 516, "collision": 0, "elevation": 3, "behavior_id": 7}, {"raw": 12804, "metatile_id": 516, "collision": 0, "elevation": 3, "behavior_id": 7}, {"raw": 12993, "metatile_id": 705, "collision": 0, "elevation": 3, "behavior_id": 0}, {"raw": 1223, "metatile_id": 199, "collision": 1, "elevation": 0, "behavior_id": 0}, {"raw": 1223, "metatile_id": 199, "collision": 1, "elevation": 0, "behavior_id": 0}, {"raw": 1223, "metatile_id": 199, "collision": 1, "elevation": 0, "behavior_id": 0}, {"raw": 1223, "metatile_id": 199, "collision": 1, "elevation": 0, "behavior_id": 0}, {"raw": 12993, "metatile_id": 705, "collision": 0, "elevation": 3, "behavior_id": 0}, {"raw": 12993, "metatile_id": 705, "collision": 0, "elevation": 3, "behavior_id": 0}, {"raw": 12804, "metatile_id": 516, "collision": 0, "elevation": 3, "behavior_id": 7}, {"raw": 12804, "metatile_id": 516, "collision": 0, "elevation": 3, "behavior_id": 7}, {"raw": 1715, "metatile_id": 691, "collision": 1, "elevation": 0, "behavior_id": 0}, {"raw": 1715, "metatile_id": 691, "collision": 1, "elevation": 0, "behavior_id": 0}, {"raw": 1715, "metatile_id": 691, "collision": 1, "elevation": 0, "behavior_id": 0}, {"raw": 12993, "metatile_id": 705, "collision": 0, "elevation": 3, "behavior_id": 0}, {"raw": 1223, "metatile_id": 199, "collision": 1, "elevation": 0, "behavior_id": 0}, {"raw": 1223, "metatile_id": 199, "collision": 1, "elevation": 0, "behavior_id": 0}, {"raw": 1223, "metatile_id": 199, "collision": 1, "elevation": 0, "behavior_id": 0}, {"raw": 1223, "metatile_id": 199, "collision": 1, "elevation": 0, "behavior_id": 0}, {"raw": 12993, "metatile_id": 705, "collision": 0, "elevation": 3, "behavior_id": 0}, {"raw": 12993, "metatile_id": 705, "collision": 0, "elevation": 3, "behavior_id": 0}, {"raw": 12993, "metatile_id": 705, "collision": 0, "elevation": 3, "behavior_id": 0}, {"raw": 1223, "metatile_id": 199, "collision": 1, "elevation": 0, "behavior_id": 0}, {"raw": 1223, "metatile_id": 199, "collision": 1, "elevation": 0, "behavior_id": 0}, {"raw": 1223, "metatile_id": 199, "collision": 1, "elevation": 0, "behavior_id": 0}, {"raw": 1223, "metatile_id": 199, "collision": 1, "elevation": 0, "behavior_id": 0}, {"raw": 1223, "metatile_id": 199, "collision": 1, "elevation": 0, "behavior_id": 0}, {"raw": 1223, "metatile_id": 199, "collision": 1, "elevation": 0, "behavior_id": 0}, {"raw": 1223, "metatile_id": 199, "collision": 1, "elevation": 0, "behavior_id": 0}, {"raw": 12993, "metatile_id": 705, "collision": 0, "elevation": 3, "behavior_id": 0}, {"raw": 12993, "metatile_id": 705, "collision": 0, "elevation": 3, "behavior_id": 0}, {"raw": 12993, "metatile_id": 705, "collision": 0, "elevation": 3, "behavior_id": 0}, {"raw": 12993, "metatile_id": 705, "collision": 0, "elevation": 3, "behavior_id": 0}, {"raw": 12993, "metatile_id": 705, "collision": 0, "elevation": 3, "behavior_id": 0}, {"raw": 1223, "metatile_id": 199, "collision": 1, "elevation": 0, "behavior_id": 0}, {"raw": 1223, "metatile_id": 199, "collision": 1, "elevation": 0, "behavior_id": 0}], "border_tiles": [{"raw": 198, "metatile_id": 198, "collision": 0, "elevation": 0, "behavior_id": 0}, {"raw": 199, "metatile_id": 199, "collision": 0, "elevation": 0, "behavior_id": 0}, {"raw": 199, "metatile_id": 199, "collision": 0, "elevation": 0, "behavior_id": 0}, {"raw": 198, "metatile_id": 198, "collision": 0, "elevation": 0, "behavior_id": 0}]}