{"id": "LAYOUT_BATTLE_FRONTIER_BATTLE_PYRAMID_FLOOR", "name": "BattleFrontier_BattlePyramidFloor_Layout", "width": 8, "height": 8, "primary_tileset": "gTileset_Building", "secondary_tileset": "gTileset_BattlePyramid", "blockdata_filepath": "data/layouts/BattleFrontier_BattlePyramidFloor/map.bin", "border_filepath": "data/layouts/BattleFrontier_BattlePyramidFloor/border.bin", "tiles": [{"raw": 653, "metatile_id": 653, "collision": 0, "elevation": 0, "behavior_id": 0}, {"raw": 12941, "metatile_id": 653, "collision": 0, "elevation": 3, "behavior_id": 0}, {"raw": 12941, "metatile_id": 653, "collision": 0, "elevation": 3, "behavior_id": 0}, {"raw": 12941, "metatile_id": 653, "collision": 0, "elevation": 3, "behavior_id": 0}, {"raw": 12941, "metatile_id": 653, "collision": 0, "elevation": 3, "behavior_id": 0}, {"raw": 12941, "metatile_id": 653, "collision": 0, "elevation": 3, "behavior_id": 0}, {"raw": 12941, "metatile_id": 653, "collision": 0, "elevation": 3, "behavior_id": 0}, {"raw": 653, "metatile_id": 653, "collision": 0, "elevation": 0, "behavior_id": 0}, {"raw": 12941, "metatile_id": 653, "collision": 0, "elevation": 3, "behavior_id": 0}, {"raw": 12941, "metatile_id": 653, "collision": 0, "elevation": 3, "behavior_id": 0}, {"raw": 653, "metatile_id": 653, "collision": 0, "elevation": 0, "behavior_id": 0}, {"raw": 653, "metatile_id": 653, "collision": 0, "elevation": 0, "behavior_id": 0}, {"raw": 653, "metatile_id": 653, "collision": 0, "elevation": 0, "behavior_id": 0}, {"raw": 653, "metatile_id": 653, "collision": 0, "elevation": 0, "behavior_id": 0}, {"raw": 653, "metatile_id": 653, "collision": 0, "elevation": 0, "behavior_id": 0}, {"raw": 653, "metatile_id": 653, "collision": 0, "elevation": 0, "behavior_id": 0}, {"raw": 12941, "metatile_id": 653, "collision": 0, "elevation": 3, "behavior_id": 0}, {"raw": 12941, "metatile_id": 653, "collision": 0, "elevation": 3, "behavior_id": 0}, {"raw": 653, "metatile_id": 653, "collision": 0, "elevation": 0, "behavior_id": 0}, {"raw": 653, "metatile_id": 653, "collision": 0, "elevation": 0, "behavior_id": 0}, {"raw": 653, "metatile_id": 653, "collision": 0, "elevation": 0, "behavior_id": 0}, {"raw": 653, "metatile_id": 653, "collision": 0, "elevation": 0, "behavior_id": 0}, {"raw": 653, "metatile_id": 653, "collision": 0, "elevation": 0, "behavior_id": 0}, {"raw": 12941, "metatile_id": 653, "collision": 0, "elevation": 3, "behavior_id": 0}, {"raw": 12941, "metatile_id": 653, "collision": 0, "elevation": 3, "behavior_id": 0}, {"raw": 12941, "metatile_id": 653, "collision": 0, "elevation": 3, "behavior_id": 0}, {"raw": 653, "metatile_id": 653, "collision": 0, "elevation": 0, "behavior_id": 0}, {"raw": 653, "metatile_id": 653, "collision": 0, "elevation": 0, "behavior_id": 0}, {"raw": 653, "metatile_id": 653, "collision": 0, "elevation": 0, "behavior_id": 0}, {"raw": 653, "metatile_id": 653, "collision": 0, "elevation": 0, "behavior_id": 0}, {"raw": 653, "metatile_id": 653, "collision": 0, "elevation": 0, "behavior_id": 0}, {"raw": 653, "metatile_id": 653, "collision": 0, "elevation": 0, "behavior_id": 0}, {"raw": 12941, "metatile_id": 653, "collision": 0, "elevation": 3, "behavior_id": 0}, {"raw": 12941, "metatile_id": 653, "collision": 0, "elevation": 3, "behavior_id": 0}, {"raw": 653, "metatile_id": 653, "collision": 0, "elevation": 0, "behavior_id": 0}, {"raw": 653, "metatile_id": 653, "collision": 0, "elevation": 0, "behavior_id": 0}, {"raw": 653, "metatile_id": 653, "collision": 0, "elevation": 0, "behavior_id": 0}, {"raw": 653, "metatile_id": 653, "collision": 0, "elevation": 0, "behavior_id": 0}, {"raw": 653, "metatile_id": 653, "collision": 0, "elevation": 0, "behavior_id": 0}, {"raw": 12941, "metatile_id": 653, "collision": 0, "elevation": 3, "behavior_id": 0}, {"raw": 653, "metatile_id": 653, "collision": 0, "elevation": 0, "behavior_id": 0}, {"raw": 12941, "metatile_id": 653, "collision": 0, "elevation": 3, "behavior_id": 0}, {"raw": 653, "metatile_id": 653, "collision": 0, "elevation": 0, "behavior_id": 0}, {"raw": 653, "metatile_id": 653, "collision": 0, "elevation": 0, "behavior_id": 0}, {"raw": 653, "metatile_id": 653, "collision": 0, "elevation": 0, "behavior_id": 0}, {"raw": 653, "metatile_id": 653, "collision": 0, "elevation": 0, "behavior_id": 0}, {"raw": 653, "metatile_id": 653, "collision": 0, "elevation": 0, "behavior_id": 0}, {"raw": 12941, "metatile_id": 653, "collision": 0, "elevation": 3, "behavior_id": 0}, {"raw": 653, "metatile_id": 653, "collision": 0, "elevation": 0, "behavior_id": 0}, {"raw": 12941, "metatile_id": 653, "collision": 0, "elevation": 3, "behavior_id": 0}, {"raw": 12941, "metatile_id": 653, "collision": 0, "elevation": 3, "behavior_id": 0}, {"raw": 12941, "metatile_id": 653, "collision": 0, "elevation": 3, "behavior_id": 0}, {"raw": 12941, "metatile_id": 653, "collision": 0, "elevation": 3, "behavior_id": 0}, {"raw": 12941, "metatile_id": 653, "collision": 0, "elevation": 3, "behavior_id": 0}, {"raw": 12941, "metatile_id": 653, "collision": 0, "elevation": 3, "behavior_id": 0}, {"raw": 12941, "metatile_id": 653, "collision": 0, "elevation": 3, "behavior_id": 0}, {"raw": 12941, "metatile_id": 653, "collision": 0, "elevation": 3, "behavior_id": 0}, {"raw": 12941, "metatile_id": 653, "collision": 0, "elevation": 3, "behavior_id": 0}, {"raw": 12941, "metatile_id": 653, "collision": 0, "elevation": 3, "behavior_id": 0}, {"raw": 12941, "metatile_id": 653, "collision": 0, "elevation": 3, "behavior_id": 0}, {"raw": 12941, "metatile_id": 653, "collision": 0, "elevation": 3, "behavior_id": 0}, {"raw": 12941, "metatile_id": 653, "collision": 0, "elevation": 3, "behavior_id": 0}, {"raw": 12941, "metatile_id": 653, "collision": 0, "elevation": 3, "behavior_id": 0}, {"raw": 653, "metatile_id": 653, "collision": 0, "elevation": 0, "behavior_id": 0}], "border_tiles": [{"raw": 1, "metatile_id": 1, "collision": 0, "elevation": 0, "behavior_id": 0}, {"raw": 1, "metatile_id": 1, "collision": 0, "elevation": 0, "behavior_id": 0}, {"raw": 1, "metatile_id": 1, "collision": 0, "elevation": 0, "behavior_id": 0}, {"raw": 1, "metatile_id": 1, "collision": 0, "elevation": 0, "behavior_id": 0}], "render_assets": {"pair_id": "gTileset_Building__gTileset_BattlePyramid", "atlas": "render/gTileset_Building__gTileset_BattlePyramid/atlas.json", "palettes": "render/gTileset_Building__gTileset_BattlePyramid/palettes.json", "metatiles": "render/gTileset_Building__gTileset_BattlePyramid/metatiles.json", "tile_anims": "render/gTileset_Building__gTileset_BattlePyramid/tile_anims.json"}}